hrcentre/__init__.py
hrcentre/admin.py
hrcentre/apps.py
hrcentre/auth_hooks.py
hrcentre/forms.py
hrcentre/models.py
hrcentre/urls.py
hrcentre/utils.py
hrcentre/views.py
hrcentre/migrations/0001_initial.py
hrcentre/migrations/0002_userscheck_negate_userscheck_operator.py
hrcentre/migrations/0003_delete_characterauditlogindata.py
hrcentre/migrations/__init__.py
hrcentre/templates/hrcentre/base.html
hrcentre/templates/hrcentre/dashboard_labels.html
hrcentre/templates/hrcentre/edit_labels.html
hrcentre/templates/hrcentre/generic_form.html
hrcentre/templates/hrcentre/group_view.html
hrcentre/templates/hrcentre/index.html
hrcentre/templates/hrcentre/label_form.html
hrcentre/templates/hrcentre/user_view.html
hrcentre/templates/hrcentre/widgets/button_group_input_option.html
hrcentre/templates/hrcentre/widgets/button_group_multiple_input.html
hrcentre/templatetags/__init__.py
hrcentre/templatetags/hrcentretags.py
aa_hr_centre-0.0.1b5.dist-info/licenses/LICENSE
aa_hr_centre-0.0.1b5.dist-info/WHEEL
aa_hr_centre-0.0.1b5.dist-info/METADATA
aa_hr_centre-0.0.1b5.dist-info/RECORD
