Metadata-Version: 2.4
Name: aa-hr-centre
Version: 0.0.1b5
Summary: HR Centre for Alliance Auth
Keywords: allianceauth,eveonline,allianceauth_hr_centre,hr,hr_centre
Author-email: Matteo Ghia <matteo.ghia@yahoo.it>
Requires-Python: ~=3.10
Classifier: Environment :: Web Environment
Classifier: Framework :: Django
Classifier: Framework :: Django :: 4
Classifier: Framework :: Django :: 4.2
Classifier: Operating System :: POSIX :: Linux
Classifier: Development Status :: 3 - Alpha
Classifier: Intended Audience :: Developers
Classifier: License :: OSI Approved :: GNU General Public License v3 (GPLv3)
Classifier: Natural Language :: English
Classifier: Programming Language :: Python :: 3
Classifier: Programming Language :: Python :: 3.10
Classifier: Programming Language :: Python :: 3.11
Classifier: Programming Language :: Python :: 3.12
Classifier: Topic :: Internet :: WWW/HTTP
Classifier: Topic :: Internet :: WWW/HTTP :: Dynamic Content
License-File: LICENSE
Requires-Dist: allianceauth~=4.6
Requires-Dist: allianceauth-corptools~=2.11
Requires-Dist: allianceauth-securegroups~=0.8
Requires-Dist: django-esi>=7.0.1
Project-URL: Changelog, https://github.com/Maestro-Zacht/aa-hr-centre/releases
Project-URL: Homepage, https://github.com/Maestro-Zacht/aa-hr-centre
Project-URL: Source, https://github.com/Maestro-Zacht/aa-hr-centre
Project-URL: Tracker, https://github.com/Maestro-Zacht/aa-hr-centre/issues
